setup.cfg
setup.py
py_token_stream/__init__.py
py_token_stream.egg-info/PKG-INFO
py_token_stream.egg-info/SOURCES.txt
py_token_stream.egg-info/dependency_links.txt
py_token_stream.egg-info/top_level.txt