Metadata-Version: 1.0
Name: py-token-stream
Version: 0.1.0
Summary: A friendlier API for working with tokens
Home-page: https://github.com/SamDudley/py-token-stream
Author: Sam Dudley
Author-email: dudley.co.uk@gmail.com
License: MIT
Platform: UNKNOWN
